emissionrpc/__init__.py
emissionrpc/__version__.py
emissionrpc/emitter.py
emissionrpc/exceptions.py
emissionrpc/helpers.py
emissionrpc/server.py
emissionrpc/specifications.py
emissionrpc-0.4.5.dist-info/DESCRIPTION.rst
emissionrpc-0.4.5.dist-info/METADATA
emissionrpc-0.4.5.dist-info/RECORD
emissionrpc-0.4.5.dist-info/WHEEL
emissionrpc-0.4.5.dist-info/metadata.json
emissionrpc-0.4.5.dist-info/top_level.txt
