Metadata-Version: 2.0
Name: emissionrpc
Version: 0.4.5
Summary: Emission, Another Wrapper JSON-RPC to Transmission
Home-page: https://github.com/Germione/emissionrpc
Author: Jerome Pradier
Author-email: jerome.pradier@gmail.com
License: MIT
Keywords: torrent json rpc
Platform: UNKNOWN
Classifier: Development Status :: 4 - Beta
Classifier: Intended Audience :: Developers
Classifier: Topic :: Software Development :: Build Tools
Classifier: License :: OSI Approved :: MIT License
Classifier: Programming Language :: Python :: 2
Classifier: Programming Language :: Python :: 2.7
Classifier: Programming Language :: Python :: 3
Classifier: Programming Language :: Python :: 3.5
Classifier: Programming Language :: Python :: 3.6
Requires-Dist: requests
